EventsPP/EventManager.py
EventsPP/__init__.py
exc/InvalidEvent.py
exc/InvalidEventTypeError.py
exc/__init__.py
EventsPP-0.0.3.dist-info/LICENSE
EventsPP-0.0.3.dist-info/METADATA
EventsPP-0.0.3.dist-info/WHEEL
EventsPP-0.0.3.dist-info/top_level.txt
EventsPP-0.0.3.dist-info/RECORD
