Metadata-Version: 2.1
Name: EventsPP
Version: 0.0.3
Summary: A package for event-driven paradigm
Home-page: https://github.com/Mateus-SF/EventsPP
Author: Mateus Ferreira
Author-email: mateus03ferreira04@gmail.com
License: MIT
Platform: UNKNOWN
License-File: LICENSE
